MANIFEST.in
README.rst
setup.py
src/zc/__init__.py
src/zc.recipe.script.egg-info/PKG-INFO
src/zc.recipe.script.egg-info/SOURCES.txt
src/zc.recipe.script.egg-info/dependency_links.txt
src/zc.recipe.script.egg-info/entry_points.txt
src/zc.recipe.script.egg-info/namespace_packages.txt
src/zc.recipe.script.egg-info/not-zip-safe
src/zc.recipe.script.egg-info/requires.txt
src/zc.recipe.script.egg-info/top_level.txt
src/zc/recipe/__init__.py
src/zc/recipe/script/README.txt
src/zc/recipe/script/__init__.py
src/zc/recipe/script/tests.py