Metadata-Version: 1.1
Name: zc.recipe.script
Version: 1.0.2
Summary: zc.buildout recipe for scripts in Unix deployments
Home-page: http://svn.zope.com/repos/main/zc.recipe.script/
Author: Fred Drake
Author-email: fred@zope.com
License: ZVSL
Keywords: deployment build
Platform: UNKNOWN
Classifier: Framework :: Buildout :: Recipe
